{
    "thema": "Bestätigung Seminarteilnahme und Nachfragen",
    "textinhalt": "Sehr geehrte Frau Müller,\n\nvielen Dank für Ihre E-Mail und die Zusage für das Seminar \"Effektives Projektmanagement\" vom 15. bis 16. November. __1__ bestätige ich Ihnen meine verbindliche Teilnahme.\n\nIch freue mich bereits sehr auf die Veranstaltung und die neuen Impulse für meine Arbeit. Gibt es Materialien, die __2__ zur Verfügung gestellt werden, __3__ ich mich optimal vorbereiten kann? Das wäre sehr hilfreich.\n\n__4__ wäre ich Ihnen dankbar, wenn Sie mir den detaillierten Zeitplan zukommen lassen könnten. Mich interessiert insbesondere, wann die Seminartage genau beginnen und enden und wann Pausen vorgesehen sind, damit ich meine An- und Abreise __5__ planen kann.\n\nIch habe das Anmeldeformular, wie gewünscht, ausgefüllt und unterschrieben. Sie finden es __6__ im Anhang dieser E-Mail.\n\nVielen Dank für Ihre Mühe.\n\nMit freundlichen Grüßen\n\nMax Mustermann",
    "options": [
        {
            "id": "a",
            "content": "anbei"
        },
        {
            "id": "b",
            "content": "außerdem"
        },
        {
            "id": "c",
            "content": "damit"
        },
        {
            "id": "d",
            "content": "ebenso"
        },
        {
            "id": "e",
            "content": "hiermit"
        },
        {
            "id": "f",
            "content": "jedoch"
        },
        {
            "id": "g",
            "content": "rechtzeitig"
        },
        {
            "id": "h",
            "content": "sobald"
        },
        {
            "id": "i",
            "content": "vorab"
        },
        {
            "id": "j",
            "content": "wegen"
        }
    ],
    "loesung": [
        {
            "blank": "1",
            "option_id": "e"
        },
        {
            "blank": "2",
            "option_id": "i"
        },
        {
            "blank": "3",
            "option_id": "c"
        },
        {
            "blank": "4",
            "option_id": "b"
        },
        {
            "blank": "5",
            "option_id": "g"
        },
        {
            "blank": "6",
            "option_id": "a"
        }
    ]
}