{
    "thema": "Rückfragen zum Arbeitsangebot als Marketing Manager",
    "textinhalt": "Sehr geehrte Frau Dr. Neumann,\n\nvielen Dank für das Arbeitsangebot für die Position als Marketing Manager, das ich gestern erhalten habe, sowie für das aufschlussreiche Gespräch in der vergangenen Woche. Ich freue mich sehr über Ihr Vertrauen und bin nach wie vor stark an dieser spannenden Herausforderung interessiert.\n\n__1__ hätte ich vor meiner endgültigen Zusage noch einige Punkte, zu denen ich um Klärung bitten möchte. Im Angebot wird der 1. September als Startdatum genannt. Wäre hier eine geringfügige Verschiebung auf den 15. September möglich, __2__ ich Mitte September eine seit langem geplante, wichtige familiäre Verpflichtung habe?\n\nIm Gespräch erwähnten Sie kurz eine mögliche Bonusstruktur. Könnten Sie mir __3__ bitte genauere Informationen zukommen lassen, wie diese gestaltet ist und an welche Ziele sie geknüpft ist?\n\nZuletzt bitte ich um eine Präzisierung __4__ des Umfangs der erwarteten internationalen Reisetätigkeit. Dies ist für meine persönliche Planung relevant.\n\n__5__ dieser offenen Fragen möchte ich nochmals betonen, wie sehr mich die Position und die Perspektiven in Ihrem Unternehmen reizen. Eine zeitnahe Rückmeldung zu diesen Punkten wäre für meine Entscheidungsfindung sehr hilfreich, __6__ bitte ich Sie um eine baldige Antwort.\n\nMit freundlichen Grüßen\n\n[Ihr Name]",
    "options": [
        {
            "id": "a",
            "content": "allerdings"
        },
        {
            "id": "b",
            "content": "außerdem"
        },
        {
            "id": "c",
            "content": "bezüglich"
        },
        {
            "id": "d",
            "content": "da"
        },
        {
            "id": "e",
            "content": "daher"
        },
        {
            "id": "f",
            "content": "dazu"
        },
        {
            "id": "g",
            "content": "dennoch"
        },
        {
            "id": "h",
            "content": "jedoch"
        },
        {
            "id": "i",
            "content": "obwohl"
        },
        {
            "id": "j",
            "content": "trotz"
        }
    ],
    "loesung": [
        {
            "blank": "1",
            "option_id": "a"
        },
        {
            "blank": "2",
            "option_id": "d"
        },
        {
            "blank": "3",
            "option_id": "f"
        },
        {
            "blank": "4",
            "option_id": "c"
        },
        {
            "blank": "5",
            "option_id": "g"
        },
        {
            "blank": "6",
            "option_id": "e"
        }
    ]
}