{
    "thema": "Bitte um Ausstellung eines Arbeitszeugnisses",
    "textinhalt": "Sehr geehrte Damen und Herren,\n\nhiermit nehme ich Bezug auf meine frühere Anstellung als Marketingassistent in Ihrem Unternehmen im Zeitraum vom 01.04.2021 bis zum 31.03.2024. Wie Sie wissen, habe ich das Unternehmen auf eigenen Wunsch verlassen, um mich beruflich neu zu orientieren.\n\n__1__ bitte ich Sie höflich um die Ausstellung eines qualifizierten Arbeitszeugnisses. Ich benötige dieses Dokument für meine weiteren Bewerbungsunterlagen, __2__ sich potenzielle neue Arbeitgeber ein umfassendes Bild von meinen bisherigen Tätigkeiten und Leistungen machen können.\n\n__3__ wäre ich Ihnen dankbar, wenn im Zeugnis wie üblich sowohl meine Aufgabenbereiche und Leistungen als auch mein Sozialverhalten bewertet werden. __4__ der genauen Inhalte und Formulierungen verlasse ich mich selbstverständlich auf die Einhaltung der gesetzlichen Vorgaben und branchenüblichen Standards.\n\nIch bitte um eine Zusendung des Zeugnisses an meine aktuelle Postadresse, die Ihnen bereits vorliegen sollte, und hoffe, dass meine Anfrage __5__ bearbeitet wird.\n\nSollten Sie Rückfragen haben oder zusätzliche Informationen benötigen, stehe ich Ihnen __6__ gerne zur Verfügung.\n\nVielen Dank für Ihre Bemühungen.\n\nMit freundlichen Grüßen\n\nMax Mustermann",
    "options": [
        {
            "id": "a",
            "content": "Bezüglich"
        },
        {
            "id": "b",
            "content": "Damit"
        },
        {
            "id": "c",
            "content": "Daher"
        },
        {
            "id": "d",
            "content": "Ferner"
        },
        {
            "id": "e",
            "content": "Jedoch"
        },
        {
            "id": "f",
            "content": "Obwohl"
        },
        {
            "id": "g",
            "content": "Selbstverständlich"
        },
        {
            "id": "h",
            "content": "Sodass"
        },
        {
            "id": "i",
            "content": "Wegen"
        },
        {
            "id": "j",
            "content": "Zeitnah"
        }
    ],
    "loesung": [
        {
            "blank": "1",
            "option_id": "c"
        },
        {
            "blank": "2",
            "option_id": "b"
        },
        {
            "blank": "3",
            "option_id": "d"
        },
        {
            "blank": "4",
            "option_id": "a"
        },
        {
            "blank": "5",
            "option_id": "j"
        },
        {
            "blank": "6",
            "option_id": "g"
        }
    ]
}